arxiv_mcp/__init__.py
arxiv_mcp/app.py
arxiv_mcp/server.py
arxiv_mcp/utils.py
arxiv_mcp/prompts/__init__.py
arxiv_mcp/prompts/prompts.py
arxiv_mcp/resources/__init__.py
arxiv_mcp/resources/resources.py
arxiv_mcp/tools/__init__.py
arxiv_mcp/tools/tools.py
iflow_mcp_daheepk_arxiv_paper_mcp-0.1.4.dist-info/licenses/LICENSE
iflow_mcp_daheepk_arxiv_paper_mcp-0.1.4.dist-info/METADATA
iflow_mcp_daheepk_arxiv_paper_mcp-0.1.4.dist-info/WHEEL
iflow_mcp_daheepk_arxiv_paper_mcp-0.1.4.dist-info/entry_points.txt
iflow_mcp_daheepk_arxiv_paper_mcp-0.1.4.dist-info/top_level.txt
iflow_mcp_daheepk_arxiv_paper_mcp-0.1.4.dist-info/RECORD
